{
  "updated": "2026-06-06T08:17:55.833Z",
  "updatedKST": "2026년 6월 6일 토요일 PM 05:17",
  "aiSummary": true,
  "sources": "📰 매일노동뉴스",
  "law": [
    {
      "title": "불붙은 도급제 최저임금 적용방안 논쟁",
      "url": "https://www.labortoday.co.kr/news/articleView.html?idxno=234924",
      "desc": "최저임금위원회에서 배달라이더를 포함해 도급제 노동자에 대한 최저임금 적용방안 논의가 본격화되고 있다. 노사 양측 찬반이 엇갈리는 가운데 구체적인 적용 대상과 방식에 대한 논의가 활발하게 이어질 수 있을지 주목된다.최저임금위는 4일 오후 정부세종청사에서 재적 위원 27명 중 24명이 참석한 가운데 3차 전원회의를 열었다. 이날 회의에서는 민주노총 몫 노동자위원인 박정훈 공공운수노조 부위원장이 ‘도급노동자 최저임금 도입방안’을 발표했다.“도급제 최저임금 지금 당장 가능하다”박정훈 부위원장이 발표한 자료에는 도급제 노동자에 대한 최저임금",
      "date": "2026년 6월 5일",
      "isoDate": "2026-06-05T06:30:04.000Z",
      "sourceLabel": "📰 매일노동뉴스",
      "main": "최저임금위원회에서 배달라이더를 포함해 도급제 노동자에 대한 최저임금 적용방안 논의가 본격화되고 있다. 노사 양측 찬반이 엇갈리는 가운데 구체적인 적용 대상과 방식에 대한 논의가 활발하게 이어질 수 있을지 주목된다.최저임금위는 4일 오후 정부세종청사에서 재적 위원 27명 중 24명이 참석한 가운데 3차 전원회의를 열었다. 이날 회의에서는 민주노총 몫 노동자위원인 박정훈 공공운수노조 부위원장이 ‘도급노동자 최저임금 도입방안’을 발표했다.“도급제 최저임금 지금 당장 가능하다”박정훈 부위원장이 발표한 자료에는 도급제 노동자에 대한 최저임금",
      "implication": "HR·노무 트렌드 관점에서 주시 필요"
    },
    {
      "title": "연장·야간근로시간 보장합의 있다면 실제 근로시간 미달해도 수당 지급해야",
      "url": "https://www.labortoday.co.kr/news/articleView.html?idxno=234879",
      "desc": "",
      "date": "2026년 6월 2일",
      "isoDate": "2026-06-02T11:18:43.000Z",
      "sourceLabel": "📰 매일노동뉴스",
      "main": "",
      "implication": "HR·노무 트렌드 관점에서 주시 필요"
    }
  ],
  "cases": [
    {
      "title": "민주노총 “정부, 해고사업장 문제 해결하라”",
      "url": "https://www.labortoday.co.kr/news/articleView.html?idxno=234933",
      "desc": "민주노총 소속 해고노동자들이 정부·국회·여당에 해고사업장 문제 해결을 요구했다. 민주노총은 4일 오후 서울 중구 서울지방고용노동청 앞에서 해고사업장 긴급 결의대회를 열고 “한국옵티칼하이테크, 이수기업, 우창코넥타, 씨스포빌, 홈플러스, 세종호텔, 우성환경, 오션비치 등 사업장에서 해고노동자 고통이 장기간 이어지고 있다”며 “문제 해결을",
      "date": "2026년 6월 5일",
      "isoDate": "2026-06-05T06:30:04.000Z",
      "sourceLabel": "📰 매일노동뉴스",
      "main": "민주노총 소속 해고노동자들이 정부·국회·여당에 해고사업장 문제 해결을 요구했다. 민주노총은 4일 오후 서울 중구 서울지방고용노동청 앞에서 해고사업장 긴급 결의대회를 열고 “한국옵티칼하이테크, 이수기업, 우창코넥타, 씨스포빌, 홈플러스, 세종호텔, 우성환경, 오션비치 등 사업장에서 해고노동자 고통이 장기간 이어지고 있다”며 “문제 해결을",
      "implication": "HR·노무 트렌드 관점에서 주시 필요"
    },
    {
      "title": "중노위 중흥건설·중흥토건 원청 사용자성 인정",
      "url": "https://www.labortoday.co.kr/news/articleView.html?idxno=234938",
      "desc": "한국타워크레인조종사노조가 중흥건설과 중흥토건을 상대로 제기한 교섭요구 사실공고 시정 재심신청 사건에서 중앙노동위원회가 초심 판정을 취소했다. 이는 개정 노동조합 및 노동관계조정법(노조법) 관련 첫 중노위 판단이다. 중노위는 4일 해당 사건에 대해 “초심 지노위 결정을 취소하고 건설사들의 원청으로서의 사용자성을 인정해 교섭요구 사실을 공",
      "date": "2026년 6월 5일",
      "isoDate": "2026-06-04T22:36:45.000Z",
      "sourceLabel": "📰 매일노동뉴스",
      "main": "한국타워크레인조종사노조가 중흥건설과 중흥토건을 상대로 제기한 교섭요구 사실공고 시정 재심신청 사건에서 중앙노동위원회가 초심 판정을 취소했다. 이는 개정 노동조합 및 노동관계조정법(노조법) 관련 첫 중노위 판단이다. 중노위는 4일 해당 사건에 대해 “초심 지노위 결정을 취소하고 건설사들의 원청으로서의 사용자성을 인정해 교섭요구 사실을 공",
      "implication": "HR·노무 트렌드 관점에서 주시 필요"
    },
    {
      "title": "학과 없앴다고 교수 면직한 대학, 법원서 제동",
      "url": "https://www.labortoday.co.kr/news/articleView.html?idxno=234915",
      "desc": "폐지된 학과의 교수를 면직한 대학의 처분이 부당하다는 법원의 판단이 나왔다. 폐과 기준을 사전에 공지하지 않았고 전환배치 노력을 하지 않았다는 이유에서다. 이번 사건에서 면직된 당사자는 교수노조 소속 간부 조합원으로 학교를 상대로 비판적 목소리를 냈던 터라 ‘표적 면직’ 의혹도 나온다.법원 “구체적인 폐과 기준 사전 공지해야”서울행정법원은 김포대 소속 두 교수가 교원소청심사위원회의 결정을 취소해 달라며 낸 소송에서 지난달 29일 원고 승소 판결을 내렸다.사립 전문대인 김포대는 2020년 신입생 충원율 100%를 달성하지 못하자 충원",
      "date": "2026년 6월 4일",
      "isoDate": "2026-06-04T06:30:04.000Z",
      "sourceLabel": "📰 매일노동뉴스",
      "main": "폐지된 학과의 교수를 면직한 대학의 처분이 부당하다는 법원의 판단이 나왔다. 폐과 기준을 사전에 공지하지 않았고 전환배치 노력을 하지 않았다는 이유에서다. 이번 사건에서 면직된 당사자는 교수노조 소속 간부 조합원으로 학교를 상대로 비판적 목소리를 냈던 터라 ‘표적 면직’ 의혹도 나온다.법원 “구체적인 폐과 기준 사전 공지해야”서울행정법원은 김포대 소속 두 교수가 교원소청심사위원회의 결정을 취소해 달라며 낸 소송에서 지난달 29일 원고 승소 판결을 내렸다.사립 전문대인 김포대는 2020년 신입생 충원율 100%를 달성하지 못하자 충원",
      "implication": "HR·노무 트렌드 관점에서 주시 필요"
    },
    {
      "title": "법원 “항의하러 경찰서 모인 조합원 긴급체포는 위법”",
      "url": "https://www.labortoday.co.kr/news/articleView.html?idxno=234906",
      "desc": "경찰이 집회 참가자를 현행범으로 연행한 것에 항의해 경찰서 앞으로 몰려간 참가자를 또다시 긴급체포한 것은 위법이라는 법원 판결이 나왔다. 3일 가 확보한 판결문을 살펴보면 법원은 1심에 이어 2심에서도 경찰의 긴급체포는 현저히 합리성을 잃은 행위로 판단했다.경찰, 한국옵티칼하이테크 집회서 조합원 연행항의하러 경찰서 간 조합원도 체포서울중앙지법 1-1민사부(재판장 임은하)는 지난달 8일 금속노조 조합원과 활동가 10명이 법무부를 상대로 낸 손해배상 소송에서 1심에 이어 원고 승소 판결했다.이들은 2024년 4월17일 경",
      "date": "2026년 6월 4일",
      "isoDate": "2026-06-04T06:30:04.000Z",
      "sourceLabel": "📰 매일노동뉴스",
      "main": "경찰이 집회 참가자를 현행범으로 연행한 것에 항의해 경찰서 앞으로 몰려간 참가자를 또다시 긴급체포한 것은 위법이라는 법원 판결이 나왔다. 3일 가 확보한 판결문을 살펴보면 법원은 1심에 이어 2심에서도 경찰의 긴급체포는 현저히 합리성을 잃은 행위로 판단했다.경찰, 한국옵티칼하이테크 집회서 조합원 연행항의하러 경찰서 간 조합원도 체포서울중앙지법 1-1민사부(재판장 임은하)는 지난달 8일 금속노조 조합원과 활동가 10명이 법무부를 상대로 낸 손해배상 소송에서 1심에 이어 원고 승소 판결했다.이들은 2024년 4월17일 경",
      "implication": "HR·노무 트렌드 관점에서 주시 필요"
    }
  ],
  "hr": [
    {
      "title": "[인사] 한국노총",
      "url": "https://www.labortoday.co.kr/news/articleView.html?idxno=234934",
      "desc": "■ 승진 △강금선 조직확대사업단 본부장 △김태룡 조직본부 본부장 △강현아 공무원본부 총괄실장 △최종환 교육홍보본부 본부장(대변인) △장인숙 여성본부 본부장 △김정연 사업지원본부 총괄실장 ■ 임명 △김종현 조직확대사업단 차장 △ 제정남 정책1본부 국장 △허윤정 정책2본부 실장 △이은주 공무원본부 총괄실장",
      "date": "2026년 6월 5일",
      "isoDate": "2026-06-05T06:30:04.000Z",
      "sourceLabel": "📰 매일노동뉴스",
      "main": "■ 승진 △강금선 조직확대사업단 본부장 △김태룡 조직본부 본부장 △강현아 공무원본부 총괄실장 △최종환 교육홍보본부 본부장(대변인) △장인숙 여성본부 본부장 △김정연 사업지원본부 총괄실장 ■ 임명 △김종현 조직확대사업단 차장 △ 제정남 정책1본부 국장 △허윤정 정책2본부 실장 △이은주 공무원본부 총괄실장",
      "implication": "HR·노무 트렌드 관점에서 주시 필요"
    },
    {
      "title": "성과급이 문제다",
      "url": "https://www.labortoday.co.kr/news/articleView.html?idxno=234872",
      "desc": "1. 야단법석은 지나갔다. 삼성전자 성과급을 두고서 한바탕 소란하더니 타결 이후 이 나라는 조용해지고 있다. 그렇지만 여전히 성과급이 문제다. 나는 오늘도 성과급에서 벗어나지 못한 채 씨름하고 있다. 5월27일 오후 나는 상대방인 피고의 소송대리인에게 원고측 상황을 설명하면서 사정해야 했다. 노조가 사측과 소송비용 문제를 정리하는 데 시간이 필요하다며 재판 진행을 최대한 늦춰달라고 주문했던 사건들 중 하나가 이날 오후 재판이 있었다. 조합원들이 집단적으로 소송한 사건이 하급심에서 승소한 뒤 원고 백아무개씨가 뒤늦게 소송을 한 사건이",
      "date": "2026년 6월 2일",
      "isoDate": "2026-06-02T06:30:04.000Z",
      "sourceLabel": "📰 매일노동뉴스",
      "main": "1. 야단법석은 지나갔다. 삼성전자 성과급을 두고서 한바탕 소란하더니 타결 이후 이 나라는 조용해지고 있다. 그렇지만 여전히 성과급이 문제다. 나는 오늘도 성과급에서 벗어나지 못한 채 씨름하고 있다. 5월27일 오후 나는 상대방인 피고의 소송대리인에게 원고측 상황을 설명하면서 사정해야 했다. 노조가 사측과 소송비용 문제를 정리하는 데 시간이 필요하다며 재판 진행을 최대한 늦춰달라고 주문했던 사건들 중 하나가 이날 오후 재판이 있었다. 조합원들이 집단적으로 소송한 사건이 하급심에서 승소한 뒤 원고 백아무개씨가 뒤늦게 소송을 한 사건이",
      "implication": "HR·노무 트렌드 관점에서 주시 필요"
    }
  ],
  "gov": [
    {
      "title": "“이재명 정부 ‘노동존중’에 성평등은 없다”",
      "url": "https://www.labortoday.co.kr/news/articleView.html?idxno=234930",
      "desc": "여성노조가 이재명 정부 출범 1년에 “‘노동존중’에 성평등은 없었다”고 평가하며 성평등 노동정책과 최저임금 인상을 촉구한다. 노조는 이재명 정부가 성평등공시제 도입과 민간고용평등상담실 복원 등을 국정과제로 제시했지만 실제 정책에서는 성평등 관점이 충분히 반영되지 않았다고 지적했다. 노조는 “여성들은 치솟는 물가 속에 저임금으로 버티고",
      "date": "2026년 6월 5일",
      "isoDate": "2026-06-05T06:30:04.000Z",
      "sourceLabel": "📰 매일노동뉴스",
      "main": "여성노조가 이재명 정부 출범 1년에 “‘노동존중’에 성평등은 없었다”고 평가하며 성평등 노동정책과 최저임금 인상을 촉구한다. 노조는 이재명 정부가 성평등공시제 도입과 민간고용평등상담실 복원 등을 국정과제로 제시했지만 실제 정책에서는 성평등 관점이 충분히 반영되지 않았다고 지적했다. 노조는 “여성들은 치솟는 물가 속에 저임금으로 버티고",
      "implication": "HR·노무 트렌드 관점에서 주시 필요"
    },
    {
      "title": "이주노동자 인권침해 ‘익명제보’ 받는다",
      "url": "https://www.labortoday.co.kr/news/articleView.html?idxno=234929",
      "desc": "정부가 이주노동자에 대한 인권침해를 예방하기 위해 익명 제보를 받고 상시모니터링을 한다. 이주노동자 밀집 사업장을 대상으로 기획감독을 실시하고 지방노동관서에 이주노동자 전담팀을 만든다. 외국인 인권리더가 현장 파악 고용노동부는 4일 이런 내용이 담긴 ‘이주노동자 인권침해 방지대책’을 마련해 시행한다고 밝혔",
      "date": "2026년 6월 5일",
      "isoDate": "2026-06-05T06:30:04.000Z",
      "sourceLabel": "📰 매일노동뉴스",
      "main": "정부가 이주노동자에 대한 인권침해를 예방하기 위해 익명 제보를 받고 상시모니터링을 한다. 이주노동자 밀집 사업장을 대상으로 기획감독을 실시하고 지방노동관서에 이주노동자 전담팀을 만든다. 외국인 인권리더가 현장 파악 고용노동부는 4일 이런 내용이 담긴 ‘이주노동자 인권침해 방지대책’을 마련해 시행한다고 밝혔",
      "implication": "HR·노무 트렌드 관점에서 주시 필요"
    },
    {
      "title": "김영훈 장관 “퇴근 뒤 업무연락에 가슴 철렁? 안 돼”",
      "url": "https://www.labortoday.co.kr/news/articleView.html?idxno=234926",
      "desc": "김영훈 고용노동부 장관이 노동자들을 만나 포괄임금 오남용 방지를 위한 의견을 들었다. 김 장관은 4일 오후 서울 금천구 가산디지털단지에 있는 야외광장에서 인근 노동자들과 간담회를 했다. 이날 간담회는 노동부가 4월9일 발표한 ‘공짜노동 근절을 위한 포괄임금 오남용 방지 지도지침’ 시행 뒤 현장의 목소리를 듣기 위해 마련됐다. <",
      "date": "2026년 6월 5일",
      "isoDate": "2026-06-05T06:30:04.000Z",
      "sourceLabel": "📰 매일노동뉴스",
      "main": "김영훈 고용노동부 장관이 노동자들을 만나 포괄임금 오남용 방지를 위한 의견을 들었다. 김 장관은 4일 오후 서울 금천구 가산디지털단지에 있는 야외광장에서 인근 노동자들과 간담회를 했다. 이날 간담회는 노동부가 4월9일 발표한 ‘공짜노동 근절을 위한 포괄임금 오남용 방지 지도지침’ 시행 뒤 현장의 목소리를 듣기 위해 마련됐다. <",
      "implication": "HR·노무 트렌드 관점에서 주시 필요"
    },
    {
      "title": "경비·청소노동자 휴게시설 개선 기관평가 반영될까",
      "url": "https://www.labortoday.co.kr/news/articleView.html?idxno=234925",
      "desc": "6·3 지방선거가 막을 내린 가운데 이재명 대통령은 곧 출범할 9기 지방정부에 경비·청소 등 시설관리 노동자의 휴게권이 제대로 보장될 수 있도록 노력해 줄 것을 요청했다. 이 대통령은 4일 오후 청와대에서 주재한 수석보좌관회의에서 “우리 사회에 소외된 영역들이 많이 있다”며 “경비와 청소 등 시설관리 노동자의 휴게권이라고 하는 게 법",
      "date": "2026년 6월 5일",
      "isoDate": "2026-06-05T06:30:04.000Z",
      "sourceLabel": "📰 매일노동뉴스",
      "main": "6·3 지방선거가 막을 내린 가운데 이재명 대통령은 곧 출범할 9기 지방정부에 경비·청소 등 시설관리 노동자의 휴게권이 제대로 보장될 수 있도록 노력해 줄 것을 요청했다. 이 대통령은 4일 오후 청와대에서 주재한 수석보좌관회의에서 “우리 사회에 소외된 영역들이 많이 있다”며 “경비와 청소 등 시설관리 노동자의 휴게권이라고 하는 게 법",
      "implication": "HR·노무 트렌드 관점에서 주시 필요"
    },
    {
      "title": "37개 점포 문 닫는 홈플러스, 3천500명 일자리 사라져",
      "url": "https://www.labortoday.co.kr/news/articleView.html?idxno=234921",
      "desc": "홈플러스가 현재 휴점 중인 전국 37개 점포를 모두 폐점하기로 하자, 노동자들이 “사실상 퇴사 강요”라며 반발했다. 홈플러스는 37개 점포 폐점과 온라인몰 일부 매각, 본사 인력조정 등을 담은 수정 회생계획안을 마련해 지난달 29일 채권단협의회 설명회에서 공유했다. 지난해 12월 이후 두 번째로 내놓은 새 회생계획안이다. 아직 서울회생",
      "date": "2026년 6월 5일",
      "isoDate": "2026-06-05T06:30:03.000Z",
      "sourceLabel": "📰 매일노동뉴스",
      "main": "홈플러스가 현재 휴점 중인 전국 37개 점포를 모두 폐점하기로 하자, 노동자들이 “사실상 퇴사 강요”라며 반발했다. 홈플러스는 37개 점포 폐점과 온라인몰 일부 매각, 본사 인력조정 등을 담은 수정 회생계획안을 마련해 지난달 29일 채권단협의회 설명회에서 공유했다. 지난해 12월 이후 두 번째로 내놓은 새 회생계획안이다. 아직 서울회생",
      "implication": "HR·노무 트렌드 관점에서 주시 필요"
    }
  ]
}